README.rst
graphite_influxdb.py
setup.cfg
setup.py
bin/maintain_cache.py
graphite_influxdb.egg-info/PKG-INFO
graphite_influxdb.egg-info/SOURCES.txt
graphite_influxdb.egg-info/dependency_links.txt
graphite_influxdb.egg-info/not-zip-safe
graphite_influxdb.egg-info/requires.txt
graphite_influxdb.egg-info/top_level.txt