Metadata-Version: 1.1
Name: graphite-influxdb
Version: 0.3
Summary: Influxdb backend plugin for graphite-web and graphite-api
Home-page: https://github.com/vimeo/graphite-influxdb
Author: Dieter Plaetinck
Author-email: dieter@vimeo.com
License: apache2
Platform: any
Classifier: Intended Audience :: Developers
Classifier: Intended Audience :: System Administrators
Classifier: License :: OSI Approved :: BSD License
Classifier: Operating System :: OS Independent
Classifier: Programming Language :: Python
Classifier: Programming Language :: Python :: 2
Classifier: Topic :: System :: Monitoring
